Workbook

Sheet COVER

Sheet SUMMARY

Sheet IS
A4: Line Items | B4: FY22 | C4: FY23 | D4: FY24 | E4: FY25 | F4: FY26 | G4: FY27 | H4: FY28 | I4: FY29 | J4: FY30 | K4: FY31
A6: REVENUE FROM OPERATIONS | B6: 219648.88 | C6: 248601.52 | D6: 275693 | E6: 284698 | F6: 294429 | G6: =F6*(1+DRIVERS!G6) -> 329760.48 | H6: =G6*(1+DRIVERS!H6) -> 369331.74 | I6: =H6*(1+DRIVERS!I6) -> 413651.55 | J6: =I6*(1+DRIVERS!J6) -> 463289.73 | K6: =J6*(1+DRIVERS!K6) -> 518884.5
A7: COST OF MATERIALS CONSUMED | B7: 109599.61 | C7: 129118.94 | D7: 124260 | E7: 135966 | F7: 147074
A8: PURCHASES OF STOCK-IN-TRADE | B8: 19029.36 | C8: 14703.41 | D8: 15498 | E8: 7724 | F8: 9753
A9: CHANGES IN INVENTORIES | B9: -331.82 | C9: -334.12 | D9: 626 | E9: -1738 | F9: -642
A10: GROSS PROFIT | B10: =B6-SUM(B7:B9) -> 91351.73 | C10: =C6-SUM(C7:C9) -> 105113.29 | D10: =D6-SUM(D7:D9) -> 135309 | E10: =E6-SUM(E7:E9) -> 142746 | F10: =F6-SUM(F7:F9) -> 138244
A11: EMPLOYEE BENEFIT EXPENSES | B11: 24744.95 | C11: 26440.9 | D11: 30052 | E11: 32581 | F11: 34131
A12: ADVERTSING & SALES PROMOTION | B12: 15991.22 | C12: 17432.52 | D12: 22823 | E12: 23972 | F12: 22746
A13: OTHER OPERATING EXPENSES | B13: =41784.27-B12 -> 25793.05 | C13: =47085.7-C12 -> 29653.18 | D13: =57277-D12 -> 34454 | E13: =60206-E12 -> 36234 | F13: =59127-F12 -> 36381
A14: EBITDA | B14: =B10-SUM(B11:B13) -> 24822.51 | C14: =C10-SUM(C11:C13) -> 31586.69 | D14: =D10-SUM(D11:D13) -> 47980 | E14: =E10-SUM(E11:E13) -> 49959 | F14: =F10-SUM(F11:F13) -> 44986 | G14: =G6*DRIVERS!G7 -> 46166.467 | H14: =H6*DRIVERS!H7 -> 51706.443 | I14: =I6*DRIVERS!I7 -> 57911.216 | J14: =J6*DRIVERS!J7 -> 64860.562 | K14: =K6*DRIVERS!K7 -> 72643.83
A15: DEPRECIATION & AMMORTIZATION | B15: 5816.72 | C15: 5012.32 | D15: 4996 | E15: 5613 | F15: 6124 | G15: =G6*DRIVERS!G8 -> 6858.88 | H15: =H6*DRIVERS!H8 -> 7681.9456 | I15: =I6*DRIVERS!I8 -> 8603.7791 | J15: =J6*DRIVERS!J8 -> 9636.2326 | K15: =K6*DRIVERS!K8 -> 10792.58
A16: EBIT | B16: =B14-B15 -> 19005.79 | C16: =C14-C15 -> 26574.37 | D16: =D14-D15 -> 42984 | E16: =E14-E15 -> 44346 | F16: =F14-F15 -> 38862 | G16: =G14-G15 -> 39307.587 | H16: =H14-H15 -> 44024.498 | I16: =I14-I15 -> 49307.437 | ... K16: =K14-K15 -> 61851.249
A17: FINANCE COSTS | B17: 1180.56 | C17: 1309.09 | D17: 473 | E17: 593 | F17: 499 | G17: =F17 -> 499 | H17: =G17 -> 499 | I17: =H17 -> 499 | J17: =I17 -> 499 | K17: =J17 -> 499
A18: OTHER INCOME | B18: 1866.91 | C18: 3953.29 | D18: 5373 | E18: 5558 | F18: 6756 | G18: =F18 -> 6756 | H18: =G18 -> 6756 | I18: =H18 -> 6756 | J18: =I18 -> 6756 | K18: =J18 -> 6756
A19: Exceptional Item | B19: 0 | C19: 703.29 | D19: 0 | E19: -430 | F19: 0 | G19: =0 -> 0 | H19: =0 -> 0 | I19: =0 -> 0 | J19: =0 -> 0 | K19: =0 -> 0
A20: PBT (PROFIT BEFORE TAX) | B20: =B16 - B17 + B18 + B19 -> 19692.14 | C20: =C16 - C17 + C18 + C19 -> 29921.86 | D20: =D16 - D17 + D18 + D19 -> 47884 | E20: =E16 - E17 + E18 + E19 -> 48881 | F20: =F16 - F17 + F18 + F19 -> 45119 | G20: =G16-G17+G18+G19 -> 45564.587 | H20: =H16-H17+H18+H19 -> 50281.498 | I20: =I16-I17+I18+I19 -> 55564.437 | J20: =J16-J17+J18+J19 -> 61481.33 | K20: =K16-K17+K18+K19 -> 68108.249
A21: TAX EXPENSE | B21: 3779.11 | C21: 5949.22 | D21: 10954 | E21: 11843 | F21: 11800 | G21: =G20*DRIVERS!G9 -> 11916.535 | H21: =H20*DRIVERS!H9 -> 13150.151 | I21: =I20*DRIVERS!I9 -> 14531.802 | J21: =J20*DRIVERS!J9 -> 16079.25 | K21: =K20*DRIVERS!K9 -> 17812.393
A22: PAT (PROFIT AFTER TAX) | B22: =B20-B21 -> 15913.03 | C22: =C20-C21 -> 23972.64 | D22: =D20-D21 -> 36930 | E22: =E20-E21 -> 37038 | F22: =F20-F21 -> 33319 | G22: =G20-G21 -> 33648.053 | H22: =H20-H21 -> 37131.346 | I22: =I20-I21 -> 41032.636 | ... K22: =K20-K21 -> 50295.857

Sheet BS
A1: MASTER BALANCE CHECK | B1: =IF(SUM(B25:F25)=0, "OK", "ERROR") -> OK
A4: Line Items | B4: FY22 | C4: FY23 | D4: FY24 | E4: FY25 | F4: FY26
A6: PROPERTY, PLANT & EQUIPMENT | B6: 29049.96 | C6: 28080.03 | D6: 28687 | E6: 29288 | F6: 34723
A7: CAPITAL WORK-IN-PROGRESS | B7: 758.98 | C7: 1548.29 | D7: 1337 | E7: 2242 | F7: 952
A8: INTANGIBLE ASSETS | B8: =79026.14 -> 79026.14 | C8: =78633.19+612 -> 79245.19 | D8: =78633+545 -> 79178 | E8: =78633+627 -> 79260 | F8: =10524+537 -> 11061
A9: OTHER NON-CURRENT ASSETS | B9: 21028.79 | C9: =4309.06+1511.61+8451.71+1139.36+4371.3 -> 19783.04 | D9: =4661+1589+5944+586+4191 -> 16971 | E9: =5586+1456+2734+2128+5241 -> 17145 | F9: =4653+19598+296+545+4105 -> 29197
A10: INVENTORIES | B10: 29722.62 | C10: 30186.26 | D10: 28350 | E10: =32805 -> 32805 | F10: =34441 -> 34441
A11: TRADE RECIVABLES | B11: 14308.39 | C11: 13781.5 | D11: 20139 | E11: =27444 -> 27444 | F11: =25660 -> 25660
A12: CASH & CASH EQUIVALENTS | B12: 21120.06 | C12: =10565.24+17781.66 -> 28346.9 | D12: =8439+8166 -> 16605 | E12: =7718+6517 -> 14235 | F12: =5259+25744 -> 31003
A13: OTHER CURRENT ASSETS | B13: 7263.17 | C13: =233.88+4409.54+556.59 -> 5200.01 | D13: =26424+3250+0+19152 -> 48826 | E13: =4666+45647+16346 -> 66659 | F13: =50628+486+7085 -> 58199
A14: TOTAL ASSETS | B14: =SUM(B6:B13) -> 202278.11 | C14: =SUM(C6:C13) -> 206171.22 | D14: =SUM(D6:D13) -> 240093 | E14: =SUM(E6:E13) -> 269078 | F14: =SUM(F6:F13) -> 225236
A16: EQUITY SHARE CAPITAL | B16: 3672.09 | C16: 3672.09 | D16: 3672 | E16: =3672 -> 3672 | F16: 3672
A17: OTHER EQUITY (RESERVE & SURPLUS) | B17: 136619.36 | C17: =151226.86+205.91 -> 151432.77 | D17: =177159+190 -> 177349 | E17: 201279 | F17: 155189
A18: LONG-TERM BORROWINGS | B18: 0 | C18: 0 | D18: 0 | E18: =0 -> 0
A19: OTHER NON-CURRENT LIABILITIES | B19: 9913.7 | C19: =2800.35+7082.27+552.45 -> 10435.07 | D19: =2591+8024+403 -> 11018 | E19: =9052+346+3652 -> 13050 | F19: =2645+7334+747 -> 10726
A20: SHORT-TERM BORROWINGS | B20: 12653.69 | C20: 0 | D20: 0 | E20: =0 -> 0
A21: TRADE PAYABLES | B21: 23641.47 | C21: =5059.3+16375.54 -> 21434.84 | D21: =4959+22647 -> 27606 | E21: =3335+25697 -> 29032 | F21: =4639+27025 -> 31664
A22: OTHER CURRENT LIABILITIES | B22: 15777.8 | C22: =1853.22+3169.52+11733.33+2183.57+256.81 -> 19196.45 | D22: =2465+11675+2833+46+3429 -> 20448 | E22: =2476+3858+12268+3106+337 -> 22045 | F22: =2513+3356+11898+5573+645 -> 23985
A23: TOTAL LIABILITIES & EQUITY | B23: =SUM(B16:B22) -> 202278.11 | C23: =SUM(C16:C22) -> 206171.22 | D23: =SUM(D16:D22) -> 240093 | E23: =SUM(E16:E22) -> 269078 | F23: =SUM(F16:F22) -> 225236
A25: BALANCE CHECK | B25: =ROUND(B14-B23,1) -> 0 | C25: =ROUND(C14-C23,1) -> 0 | D25: =ROUND(D14-D23,1) -> 0 | E25: =ROUND(E14-E23,1) -> 0 | F25: =ROUND(F14-F23,1) -> 0

Sheet CFS
A4: LINE ITEMS | C4: FY23 | D4: FY24 | E4: FY25 | F4: FY26
A6: PROFIT AFTER TAX (PAT) | C6: =IS!C22 -> 23972.64 | D6: =IS!D22 -> 36930 | E6: =IS!E22 -> 37038 | F6: =IS!F22 -> 33319
A7: DEPRECIATION & AMMORTIZATION | C7: =IS!C15 -> 5012.32 | D7: =IS!D15 -> 4996 | E7: =IS!E15 -> 5613 | F7: =IS!F15 -> 6124
A8: CHANGE IN OPERATING ASSETS | C8: =(BS!B10+BS!B11+BS!B13+BS!B9) - (BS!C10+BS!C11+BS!C13+BS!C9) -> 3372.16 | D8: =(BS!C10+BS!C11+BS!C13+BS!C9) - (BS!D10+BS!D11+BS!D13+BS!D9) -> -45335.19 | E8: =(BS!D10+BS!D11+BS!D13+BS!D9) - (BS!E10+BS!E11+BS!E13+BS!E9) -> -29767 | F8: =(BS!E10+BS!E11+BS!E13+BS!E9) - (BS!F10+BS!F11+BS!F13+BS!F9) -> -3444
A9: CHANGE IN OPERATING LIABILITIES | C9: =(BS!C21+BS!C22+BS!C19) - (BS!B21+BS!B22+BS!B19) -> 1733.39 | D9: =(BS!D21+BS!D22+BS!D19) - (BS!C21+BS!C22+BS!C19) -> 8005.64 | E9: =(BS!E21+BS!E22+BS!E19) - (BS!D21+BS!D22+BS!D19) -> 5055 | F9: =(BS!F21+BS!F22+BS!F19) - (BS!E21+BS!E22+BS!E19) -> 2248
A10: CASH FLOW FROM OPERATIONS | C10: =SUM(C6:C9) -> 34090.51 | D10: =SUM(D6:D9) -> 4596.45 | E10: =SUM(E6:E9) -> 17939 | F10: =SUM(F6:F9) -> 38247
A12: CAPITAL EXPENDITURE & INTANGIBLES | C12: =(BS!B6+BS!B7+BS!B8) - (BS!C6+BS!C7+BS!C8) - IS!C15 -> -5050.75 | D12: =(BS!C6+BS!C7+BS!C8) - (BS!D6+BS!D7+BS!D8) - IS!D15 -> -5324.49 | E12: =(BS!D6+BS!D7+BS!D8) - (BS!E6+BS!E7+BS!E8) - IS!E15 -> -7201 | F12: =(BS!E6+BS!E7+BS!E8) - (BS!F6+BS!F7+BS!F8) - IS!F15 -> 57930
A13: CASH FLOW FROM INVESTING | C13: =C12 -> -5050.75 | D13: =D12 -> -5324.49 | E13: =E12 -> -7201 | F13: =F12 -> 57930
A15: CHANGE IN TOTAL BORROWINGS | C15: =(BS!C18+BS!C20) - (BS!B18+BS!B20) -> -12653.69 | D15: =(BS!D18+BS!D20) - (BS!C18+BS!C20) -> 0 | E15: =(BS!E18+BS!E20) - (BS!D18+BS!D20) -> 0 | F15: =(BS!F18+BS!F20) - (BS!E18+BS!E20) -> 0
A16: DIVIDENDS PAID & EQUITY CHANGES | C16: =(BS!C16+BS!C17) - (BS!B16+BS!B17) - IS!C22 -> -9159.23 | D16: =(BS!D16+BS!D17) - (BS!C16+BS!C17) - IS!D22 -> -11013.86 | E16: =(BS!E16+BS!E17) - (BS!D16+BS!D17) - IS!E22 -> -13108 | F16: =(BS!F16+BS!F17) - (BS!E16+BS!E17) - IS!F22 -> -79409
A17: CASH FLOW FROM FINANCING | C17: =C15+C16 -> -21812.92 | D17: =D15+D16 -> -11013.86 | E17: =E15+E16 -> -13108 | F17: =F15+F16 -> -79409
A19: NET CHANGE IN CASH | C19: =C10+C13+C17 -> 7226.84 | D19: =D10+D13+D17 -> -11741.9 | E19: =E10+E13+E17 -> -2370 | F19: =F10+F13+F17 -> 16768
A20: BEGINNING CASH BALANCE | C20: =BS!B12 -> 21120.06 | D20: =BS!C12 -> 28346.9 | E20: =BS!D12 -> 16605 | F20: =BS!E12 -> 14235
A21: CALCULATED ENDING CASH | C21: =C19+C20 -> 28346.9 | D21: =D19+D20 -> 16605 | E21: =E19+E20 -> 14235 | F21: =F19+F20 -> 31003
A23: CASH MATCH CHECK | C23: =ROUND(C21-BS!C12,1) -> 0 | D23: =ROUND(D21-BS!D12,1) -> 0 | E23: =ROUND(E21-BS!E12,1) -> 0 | F23: =ROUND(F21-BS!F12,1) -> 0

Sheet SCHEDULES

Sheet DRIVERS
D1: ACTIVE SCENARIO | E1: Base
A4: LINE ITEMS | B4: FY22 | C4: FY23 | D4: FY24 | E4: FY25 | F4: FY26 | G4: FY27 | H4: FY28 | I4: FY29 | J4: FY30 | K4: FY31
A6: REVENUE GROWTH | C6: =(IS!C6/IS!B6)-1 -> 0.13181328 | D6: =(IS!D6/IS!C6)-1 -> 0.10897552 | E6: =(IS!E6/IS!D6)-1 -> 0.032663143 | F6: =(IS!F6/IS!E6)-1 -> 0.034180079 | G6: =INDEX($C$17:$C$19, MATCH($E$1, $B$17:$B$19, 0)) -> 0.12 | H6: =INDEX($C$17:$C$19, MATCH($E$1, $B$17:$B$19, 0)) -> 0.12 | I6: =INDEX($C$17:$C$19, MATCH($E$1, $B$17:$B$19, 0)) -> 0.12 | J6: =INDEX($C$17:$C$19, MATCH($E$1, $B$17:$B$19, 0)) -> 0.12 | K6: =INDEX($C$17:$C$19, MATCH($E$1, $B$17:$B$19, 0)) -> 0.12
A7: EBITDA MARGIN | B7: =IS!B14/IS!B6 -> 0.11300995 | C7: =IS!C14/IS!C6 -> 0.12705751 | D7: =IS!D14/IS!D6 -> 0.17403416 | E7: =IS!E14/IS!E6 -> 0.17548068 | F7: =IS!F14/IS!F6 -> 0.15279066 | G7: =INDEX($D$17:$D$19, MATCH($E$1, $B$17:$B$19, 0)) -> 0.14 | H7: =INDEX($D$17:$D$19, MATCH($E$1, $B$17:$B$19, 0)) -> 0.14 | I7: =INDEX($D$17:$D$19, MATCH($E$1, $B$17:$B$19, 0)) -> 0.14 | J7: =INDEX($D$17:$D$19, MATCH($E$1, $B$17:$B$19, 0)) -> 0.14 | K7: =INDEX($D$17:$D$19, MATCH($E$1, $B$17:$B$19, 0)) -> 0.14
A8: DEPRECIATION AS % OF SALES | B8: =IS!B15/IS!B6 -> 0.026481901 | C8: =IS!C15/IS!C6 -> 0.020162065 | D8: =IS!D15/IS!D6 -> 0.018121606 | E8: =IS!E15/IS!E6 -> 0.019715628 | F8: =IS!F15/IS!F6 -> 0.020799582 | G8: =F8 -> 0.020799582 | H8: =G8 -> 0.020799582 | I8: =H8 -> 0.020799582 | J8: =I8 -> 0.020799582 | K8: =J8 -> 0.020799582
A9: EFFECTIVE TAX RATE | B9: =IS!B21/IS!B20 -> 0.19190956 | C9: =IS!C21/IS!C20 -> 0.19882521 | D9: =IS!D21/IS!D20 -> 0.22876117 | E9: =IS!E21/IS!E20 -> 0.24228228 | F9: =IS!F21/IS!F20 -> 0.26153062 | G9: =F9 -> 0.26153062 | H9: =G9 -> 0.26153062 | I9: =H9 -> 0.26153062 | J9: =I9 -> 0.26153062 | K9: =J9 -> 0.26153062
A11: RECEIVABLE DAYS | B11: =(BS!B11/IS!B6)*365 -> 23.776868 | C11: =(BS!C11/IS!C6)*365 -> 20.234178 | D11: =(BS!D11/IS!D6)*365 -> 26.662755 | E11: =(BS!E11/IS!E6)*365 -> 35.184863 | F11: =(BS!F11/IS!F6)*365 -> 31.810386 | G11: =F11 -> 31.810386 | H11: =G11 -> 31.810386 | I11: =H11 -> 31.810386 | J11: =I11 -> 31.810386 | K11: =J11 -> 31.810386
A12: INVENTORY DAYS | B12: =(BS!B10/IS!B6)*365 -> 49.391357 | C12: =(BS!C10/IS!C6)*365 -> 44.319861 | D12: =(BS!D10/IS!D6)*365 -> 37.533597 | E12: =(BS!E10/IS!E6)*365 -> 42.057988 | F12: =(BS!F10/IS!F6)*365 -> 42.696083 | G12: =F12 -> 42.696083 | H12: =G12 -> 42.696083 | I12: =H12 -> 42.696083 | J12: =I12 -> 42.696083 | K12: =J12 -> 42.696083
A13: PAYABLE DAYS | B13: =(BS!B21/IS!B6)*365 -> 39.286048 | C13: =(BS!C21/IS!C6)*365 -> 31.470912 | D13: =(BS!D21/IS!D6)*365 -> 36.548588 | E13: =(BS!E21/IS!E6)*365 -> 37.220774 | F13: =(BS!F21/IS!F6)*365 -> 39.25347 | G13: =F13 -> 39.25347 | H13: =G13 -> 39.25347 | I13: =H13 -> 39.25347 | J13: =I13 -> 39.25347 | K13: =J13 -> 39.25347
A16: SCENARIO ASSUMPTIONS (FY27-FY31) | C16: REVENUE GROWTH | D16: EBITDA MARGIN
B17: BASE | C17: 0.12 | D17: 0.14
B18: BULL | C18: 0.15 | D18: 0.16
B19: BEAR | C19: 0.08 | D19: 0.11

Sheet DCF
A4: LINE ITEMS | B4: FY26 | C4: FY27 | D4: FY28 | E4: FY29 | F4: FY30 | G4: FY31
A6: EBIT (OPERATING PROFIT) | B6: =IS!F16 -> 38862 | C6: =IS!G16 -> 39307.587 | D6: =IS!H16 -> 44024.498 | E6: =IS!I16 -> 49307.437 | F6: =IS!J16 -> 55224.33 | G6: =IS!K16 -> 61851.249
A7: LESS: ADJUSTED CASH TAXES | B7: =B6*DRIVERS!F9 -> 10163.603 | C7: =C6*DRIVERS!G9 -> 10280.138 | D7: =D6*DRIVERS!H9 -> 11513.754 | E7: =E6*DRIVERS!I9 -> 12895.405 | F7: =F6*DRIVERS!J9 -> 14442.853 | G7: =G6*DRIVERS!K9 -> 16175.996
A8: NOPAT | B8: =B6-B7 -> 28698.397 | C8: =C6-C7 -> 29027.45 | D8: =D6-D7 -> 32510.744 | E8: =E6-E7 -> 36412.033 | F8: =F6-F7 -> 40781.477 | G8: =G6-G7 -> 45675.254
A9: ADD: DEPRECIATION & AMMORTIZATION | B9: =IS!F15 -> 6124 | C9: =IS!G15 -> 6858.88 | D9: =IS!H15 -> 7681.9456 | E9: =IS!I15 -> 8603.7791 | F9: =IS!J15 -> 9636.2326 | G9: =IS!K15 -> 10792.58
A10: LESS: CAPITAL EXPENDITURES (CapEx)) | B10: =B9 -> 6124 | C10: =C9 -> 6858.88 | D10: =D9 -> 7681.9456 | E10: =E9 -> 8603.7791 | F10: =F9 -> 9636.2326 | G10: =G9 -> 10792.58
A11: LESS: CHANGE IN NET WORKING CAPITAL | B11: =0 -> 0 | C11: =C19-B19 -> 3412.44 | D11: =D19-C19 -> 3821.9328 | E11: =E19-D19 -> 4280.5647 | F11: =F19-E19 -> 4794.2325 | G11: =G19-F19 -> 5369.5404
A12: UNLEVERED FREE CASH FLOW | B12: =B8+B9-B10-B11 -> 28698.397 | C12: =C8+C9-C10-C11 -> 25615.01 | D12: =D8+D9-D10-D11 -> 28688.811 | E12: =E8+E9-E10-E11 -> 32131.468 | F12: =F8+F9-F10-F11 -> 35987.244 | G12: =G8+G9-G10-G11 -> 40305.713
A15: NET WORKING CAPITAL SCHEDULE
A16: TRADE RECEIVABLES | B16: =(DRIVERS!F11/365)*IS!F6 -> 25660 | C16: =(DRIVERS!G11/365)*IS!G6 -> 28739.2 | D16: =(DRIVERS!H11/365)*IS!H6 -> 32187.904 | E16: =(DRIVERS!I11/365)*IS!I6 -> 36050.452 | F16: =(DRIVERS!J11/365)*IS!J6 -> 40376.507 | G16: =(DRIVERS!K11/365)*IS!K6 -> 45221.688
A17: INVENTORIES | B17: =(DRIVERS!F12/365)*IS!F6 -> 34441 | C17: =(DRIVERS!G12/365)*IS!G6 -> 38573.92 | D17: =(DRIVERS!H12/365)*IS!H6 -> 43202.79 | E17: =(DRIVERS!I12/365)*IS!I6 -> 48387.125 | F17: =(DRIVERS!J12/365)*IS!J6 -> 54193.58 | G17: =(DRIVERS!K12/365)*IS!K6 -> 60696.81
A18: TRADE PAYABLES | B18: =(DRIVERS!F13/365)*IS!F6 -> 31664 | C18: =(DRIVERS!G13/365)*IS!G6 -> 35463.68 | D18: =(DRIVERS!H13/365)*IS!H6 -> 39719.322 | E18: =(DRIVERS!I13/365)*IS!I6 -> 44485.64 | F18: =(DRIVERS!J13/365)*IS!J6 -> 49823.917 | G18: =(DRIVERS!K13/365)*IS!K6 -> 55802.787
A19: TOTAL NET WORKING CAPITAL | B19: =B16+B17-B18 -> 28437 | C19: =C16+C17-C18 -> 31849.44 | D19: =D16+D17-D18 -> 35671.373 | E19: =E16+E17-E18 -> 39951.938 | F19: =F16+F17-F18 -> 44746.17 | G19: =G16+G17-G18 -> 50115.71
A22: WACC (DISCOUNT RATE) | B22: 0.11
A23: TERMINAL GROWTH RATE | B23: 0.05
A25: YEAR NUMBER | B25: 0 | C25: 1 | D25: 2 | E25: 3 | F25: 4 | G25: 5
A26: DISCOUNT FACTOR | C26: =(1+$B$22)^C25 -> 1.11 | D26: =(1+$B$22)^D25 -> 1.2321 | E26: =(1+$B$22)^E25 -> 1.367631 | F26: =(1+$B$22)^F25 -> 1.5180704 | G26: =(1+$B$22)^G25 -> 1.6850582
A27: PV OF FREE CASH FLOW | C27: =C12/C26 -> 23076.585 | D27: =D12/D26 -> 23284.482 | E27: =E12/E26 -> 23494.252 | F27: =F12/F26 -> 23705.912 | G27: =G12/G26 -> 23919.479
A29: TERMINAL VALUE | G29: =(G12*(1+$B$23))/($B$22-$B$23) -> 705349.99
A30: PV OF TERMINAL VALUE | G30: =G29/G26 -> 418590.89
A32: ENTERPISE VALUE | B32: =SUM(C27:G27)+G30 -> 536071.6
A33: ADD: CASH & EQUIVALENTS | B33: =BS!F12 -> 31003
A34: LESS: TOTAL DEBT | B34: =BS!F18+BS!F20 -> 0
A35: EQUITY VALUE | B35: =B32+B33-B34 -> 567074.6
A36: SHARES OUTSTANDING | B36: 3672.09
A37: IMPLIED SHARE PRICE | B37: =B35/B36 -> 154.42829
B40: =B37 -> 154.42829 | C40: 0.04 | D40: 0.045 | E40: 0.05 | F40: 0.055 | G40: 0.06
B41: 0.09 | C41: 190.63453 | D41: 207.91417 | E41: 229.51373 | F41: 257.28458 | G41: 294.31239
B42: 0.1 | C42: 159.45747 | D42: 170.81643 | E42: 184.44718 | F42: 201.10699 | G42: 221.93175
B43: 0.11 | C43: 137.21309 | D43: 145.15857 | E43: 154.42829 | F43: 165.38342 | G43: 178.52958
B44: 0.12 | C44: 120.55064 | D44: 126.36363 | E44: 133.00706 | F44: 140.67255 | G44: 149.61561
B45: 0.13 | C45: 107.60861 | D45: 112.00856 | E45: 116.95851 | F45: 122.56845 | G45: 128.97981
